odoo_lead_manager/__init__.py
odoo_lead_manager/add_leadreport.py
odoo_lead_manager/cli.py
odoo_lead_manager/client.py
odoo_lead_manager/daily_distribution.py
odoo_lead_manager/distribution.py
odoo_lead_manager/filters.py
odoo_lead_manager/lead_manager.py
odoo_lead_manager-1.3.2.dist-info/licenses/LICENSE
odoo_lead_manager-1.3.2.dist-info/METADATA
odoo_lead_manager-1.3.2.dist-info/WHEEL
odoo_lead_manager-1.3.2.dist-info/entry_points.txt
odoo_lead_manager-1.3.2.dist-info/top_level.txt
odoo_lead_manager-1.3.2.dist-info/RECORD
