Metadata-Version: 2.4
Name: odoo-lead-manager
Version: 1.3.2
Summary: Comprehensive Python package for managing Odoo leads with smart distribution
Home-page: https://github.com/example/odoo-lead-manager
Author: Lead Management Team
Author-email: Lead Management Team <team@example.com>
Maintainer-email: Lead Management Team <team@example.com>
License: MIT
Project-URL: Homepage, https://github.com/example/odoo-lead-manager
Project-URL: Documentation, https://github.com/example/odoo-lead-manager#readme
Project-URL: Repository, https://github.com/example/odoo-lead-manager
Project-URL: Bug Tracker, https://github.com/example/odoo-lead-manager/issues
Keywords: odoo,lead,management,distribution,crm,sales,automation
Classifier: Development Status :: 4 - Beta
Classifier: Intended Audience :: Developers
Classifier: Intended Audience :: System Administrators
Classifier: License :: OSI Approved :: MIT License
Classifier: Operating System :: OS Independent
Classifier: Programming Language :: Python :: 3
Classifier: Programming Language :: Python :: 3.8
Classifier: Programming Language :: Python :: 3.9
Classifier: Programming Language :: Python :: 3.10
Classifier: Programming Language :: Python :: 3.11
Classifier: Programming Language :: Python :: 3.12
Classifier: Topic :: Office/Business
Classifier: Topic :: Software Development :: Libraries :: Python Modules
Classifier: Topic :: Database
Requires-Python: >=3.8
License-File: LICENSE
Requires-Dist: odoorpc>=0.8.0
Requires-Dist: python-dateutil>=2.8.0
Requires-Dist: pandas>=1.3.0
Requires-Dist: numpy>=1.21.0
Requires-Dist: pydantic>=1.8.0
Requires-Dist: python-dotenv>=0.19.0
Requires-Dist: loguru>=0.6.0
Requires-Dist: requests>=2.25.0
Requires-Dist: pyyaml>=5.4.0
Requires-Dist: tabulate>=0.8.9
Requires-Dist: mcp>=1.0.0
Provides-Extra: dev
Requires-Dist: pytest>=6.0; extra == "dev"
Requires-Dist: pytest-cov>=2.0; extra == "dev"
Requires-Dist: pytest-mock>=3.0; extra == "dev"
Requires-Dist: black>=22.0; extra == "dev"
Requires-Dist: flake8>=4.0; extra == "dev"
Requires-Dist: mypy>=0.910; extra == "dev"
Provides-Extra: mcp
Requires-Dist: fastmcp>=0.4.0; extra == "mcp"
Requires-Dist: typing-extensions>=4.0.0; extra == "mcp"
Dynamic: author
Dynamic: home-page
Dynamic: license-file
Dynamic: requires-python
